FreezeUI/__init__.py
FreezeUI/__main__.py
FreezeUI/editor_window.py
FreezeUI/exe_win.py
FreezeUI/msi_win.py
FreezeUI/assets/exe_template.txt
FreezeUI/assets/exe_text.png
FreezeUI/assets/icon.gif
FreezeUI/assets/icon.ico
FreezeUI/assets/msi_template.txt
FreezeUI/assets/msi_text.png
FreezeUI/assets/pyicon.svg
FreezeUI-0.0.4.data/data/bitmaps/exe_text.png
FreezeUI-0.0.4.data/data/bitmaps/icon.gif
FreezeUI-0.0.4.data/data/bitmaps/icon.ico
FreezeUI-0.0.4.data/data/bitmaps/msi_text.png
FreezeUI-0.0.4.data/data/bitmaps/pyicon.svg
FreezeUI-0.0.4.data/data/text files/exe_template.txt
FreezeUI-0.0.4.data/data/text files/msi_template.txt
FreezeUI-0.0.4.dist-info/LICENSE
FreezeUI-0.0.4.dist-info/METADATA
FreezeUI-0.0.4.dist-info/WHEEL
FreezeUI-0.0.4.dist-info/entry_points.txt
FreezeUI-0.0.4.dist-info/top_level.txt
FreezeUI-0.0.4.dist-info/RECORD
